tenant/__init__.py
tenant/db_router.py
tenant/filters.py
tenant/routes.py
tenant/tenant.py
tenant/util.py
tenant_django-0.0.3.dist-info/LICENSE
tenant_django-0.0.3.dist-info/METADATA
tenant_django-0.0.3.dist-info/WHEEL
tenant_django-0.0.3.dist-info/top_level.txt
tenant_django-0.0.3.dist-info/RECORD
