Metadata-Version: 2.1
Name: tenant-django
Version: 0.0.3
Summary: A multitenant multidatabase middleware for django
Author-email: Stamatios Stamou Jr <ssjunior@gmail.com>
Project-URL: Homepage, https://github.com/ssjunior/tenant-django
Project-URL: Bug Tracker, https://github.com/ssjunior/tenant-django/issues
Classifier: Programming Language :: Python :: 3
Classifier: License :: OSI Approved :: MIT License
Classifier: Operating System :: OS Independent
Requires-Python: >=3.7
License-File: LICENSE
